pytopo3d/__init__.py
pytopo3d/cli/__init__.py
pytopo3d/cli/command.py
pytopo3d/cli/parser.py
pytopo3d/core/__init__.py
pytopo3d/core/compliance.py
pytopo3d/core/optimizer.py
pytopo3d/preprocessing/__init__.py
pytopo3d/preprocessing/geometry.py
pytopo3d/runners/__init__.py
pytopo3d/runners/experiment.py
pytopo3d/runners/pipeline.py
pytopo3d/utils/__init__.py
pytopo3d/utils/assembly.py
pytopo3d/utils/boundary.py
pytopo3d/utils/export.py
pytopo3d/utils/filter.py
pytopo3d/utils/import_design_space.py
pytopo3d/utils/logger.py
pytopo3d/utils/metrics.py
pytopo3d/utils/obstacles.py
pytopo3d/utils/oc_update.py
pytopo3d/utils/results_manager.py
pytopo3d/utils/solver.py
pytopo3d/utils/stiffness.py
pytopo3d/visualization/__init__.py
pytopo3d/visualization/animation.py
pytopo3d/visualization/display.py
pytopo3d/visualization/runner.py
pytopo3d/visualization/visualizer.py
pytopo3d-0.1.0.dist-info/licenses/LICENSE
pytopo3d-0.1.0.dist-info/METADATA
pytopo3d-0.1.0.dist-info/WHEEL
pytopo3d-0.1.0.dist-info/top_level.txt
pytopo3d-0.1.0.dist-info/RECORD
