Metadata-Version: 2.4
Name: pytopo3d
Version: 0.1.0
Summary: 3D SIMP Topology Optimization Framework for Python
Home-page: https://github.com/jihoonkim888/PyTopo3D
Author: Jihoon Kim, Namwoo Kang
Author-email: Jihoon Kim <jihoonkim888@example.com>, Namwoo Kang <example@example.com>
License: MIT
Project-URL: Homepage, https://github.com/jihoonkim888/PyTopo3D
Project-URL: Bug Tracker, https://github.com/jihoonkim888/PyTopo3D/issues
Project-URL: Documentation, https://github.com/jihoonkim888/PyTopo3D
Project-URL: Source Code, https://github.com/jihoonkim888/PyTopo3D
Keywords: topology optimization,SIMP,structural optimization,3D,finite element
Classifier: Programming Language :: Python :: 3
Classifier: Programming Language :: Python :: 3.10
Classifier: License :: OSI Approved :: MIT License
Classifier: Operating System :: OS Independent
Classifier: Topic :: Scientific/Engineering
Classifier: Topic :: Scientific/Engineering :: Mathematics
Requires-Python: >=3.10
License-File: LICENSE
Requires-Dist: numpy
Requires-Dist: pandas
Requires-Dist: matplotlib
Requires-Dist: scipy
Requires-Dist: scikit-image
Requires-Dist: networkx
Requires-Dist: pillow
Requires-Dist: plotly
Requires-Dist: tqdm
Requires-Dist: trimesh
Requires-Dist: psutil
Requires-Dist: pypardiso
Provides-Extra: dev
Requires-Dist: jupyter; extra == "dev"
Requires-Dist: jupyterlab; extra == "dev"
Dynamic: author
Dynamic: home-page
Dynamic: license-file
Dynamic: requires-python
